{"beet salad": {"overall_score": 8.0, "sentiment_score": 8.0}, "grilled octopus": {"overall_score": 2.0, "sentiment_score": 3.0}, "hamachi crudo": {"overall_score": 6.0, "sentiment_score": 4.0}, "seared sonoma foie gras": {"overall_score": 5.0, "sentiment_score": 7.0}, "uni cr\u00e8me br\u00fbl\u00e9e": {"overall_score": 4.0, "sentiment_score": 5.0}, "maine lobster ramen": {"overall_score": 7.0, "sentiment_score": 6.0}, "black cod": {"overall_score": 1.0, "sentiment_score": 2.0}, "duck breast": {"overall_score": 3.0, "sentiment_score": 1.0}}