{"hot pastrami and swiss sandwich": {"overall_score": 8.0, "sentiment_score": 10.0}, "pastrami royal sandwich": {"overall_score": 10.0, "sentiment_score": 9.0}, "hot mediterranean sandwich": {"overall_score": 2.0, "sentiment_score": 2.0}, "turkey royal sandwich": {"overall_score": 7.0, "sentiment_score": 6.0}, "the club sandwich": {"overall_score": 9.0, "sentiment_score": 8.0}, "chipotle turkey club sandwich": {"overall_score": 1.0, "sentiment_score": 1.0}, "chicken mediterranean sandwich": {"overall_score": 4.0, "sentiment_score": 4.0}, "chicken pesto basil sandwich": {"overall_score": 3.0, "sentiment_score": 3.0}, "sante fe chicken sandwich": {"overall_score": 5.0, "sentiment_score": 7.0}, "chipotle chicken sandwich": {"overall_score": 6.0, "sentiment_score": 5.0}}