{"cucumber salad with peanuts": {"overall_score": 8.0, "sentiment_score": 8.0}, "shredded pig ear": {"overall_score": 2.0, "sentiment_score": 6.0}, "house special sizzling rice": {"overall_score": 13.5, "sentiment_score": 14.0}, "honey chili tofu": {"overall_score": 6.0, "sentiment_score": 4.0}, "braised beef and beef tendon noodle soup": {"overall_score": 11.0, "sentiment_score": 11.0}, "vegetarian noodle soup": {"overall_score": 3.0, "sentiment_score": 5.0}, "pork knuckle noodle soup": {"overall_score": 16.0, "sentiment_score": 16.0}, "house spicy chicken noodle soup": {"overall_score": 7.0, "sentiment_score": 12.0}, "dandan noodles": {"overall_score": 9.0, "sentiment_score": 10.0}, "shanghai soup dumplings": {"overall_score": 10.0, "sentiment_score": 7.0}, "chili oil wontons": {"overall_score": 15.0, "sentiment_score": 13.0}, "pork dumplings in chili oil": {"overall_score": 12.0, "sentiment_score": 9.0}, "boiled cabbage and chicken dumplings": {"overall_score": 4.0, "sentiment_score": 1.0}, "boiled corn and chicken dumplings": {"overall_score": 1.0, "sentiment_score": 2.0}, "boiled vegetarian dumplings": {"overall_score": 13.5, "sentiment_score": 15.0}, "boiled black sesame mochi": {"overall_score": 5.0, "sentiment_score": 3.0}}