{"panzerotti": {"overall_score": 3.0, "sentiment_score": 5.0}, "insalata di spinaci": {"overall_score": 24.0, "sentiment_score": 39.0}, "salsiccia": {"overall_score": 49.0, "sentiment_score": 47.0}, "polpette": {"overall_score": 18.5, "sentiment_score": 17.0}, "penne san francisco": {"overall_score": 46.0, "sentiment_score": 37.0}, "spaghetti allo scoglio": {"overall_score": 14.0, "sentiment_score": 11.0}, "spaghetti alle vongole": {"overall_score": 10.5, "sentiment_score": 20.0}, "ravioli aragosta": {"overall_score": 28.5, "sentiment_score": 25.0}, "spaghetti al salmone": {"overall_score": 40.0, "sentiment_score": 36.0}, "fettuccine pescatore": {"overall_score": 26.0, "sentiment_score": 26.0}, "penne alla vodka": {"overall_score": 47.0, "sentiment_score": 46.0}, "spaghetti carbonara": {"overall_score": 16.5, "sentiment_score": 15.0}, "spaghetti polpette": {"overall_score": 6.0, "sentiment_score": 10.0}, "spaghetti salsiccia": {"overall_score": 36.5, "sentiment_score": 34.0}, "fettuccine mona lisa": {"overall_score": 22.0, "sentiment_score": 23.0}, "fettuccine leonardo": {"overall_score": 23.0, "sentiment_score": 12.0}, "penne al forno alla calabrese": {"overall_score": 34.0, "sentiment_score": 28.0}, "lasagna di casa": {"overall_score": 13.0, "sentiment_score": 14.0}, "rigatoni aldon smith": {"overall_score": 20.0, "sentiment_score": 18.0}, "rigatoni osilio": {"overall_score": 1.0, "sentiment_score": 4.0}, "chicken saltimbocca": {"overall_score": 16.5, "sentiment_score": 13.0}, "chicken san marino": {"overall_score": 30.0, "sentiment_score": 21.0}, "chicken san francisco": {"overall_score": 9.0, "sentiment_score": 8.0}, "involtini mona lisa": {"overall_score": 5.0, "sentiment_score": 1.0}, "tagliata di manzo": {"overall_score": 10.5, "sentiment_score": 7.0}, "vitello mona lisa": {"overall_score": 48.0, "sentiment_score": 49.0}, "la voce del mare": {"overall_score": 42.0, "sentiment_score": 38.0}, "mixed seafood grill": {"overall_score": 31.0, "sentiment_score": 40.0}, "parmigiana di melanzane": {"overall_score": 41.0, "sentiment_score": 44.0}, "spaghetti aglio e olio": {"overall_score": 27.0, "sentiment_score": 30.0}, "spaghetti al pomodoro": {"overall_score": 8.0, "sentiment_score": 9.0}, "penne salsa rosa": {"overall_score": 35.0, "sentiment_score": 32.0}, "ravioli ai quattro formaggi": {"overall_score": 39.0, "sentiment_score": 45.0}, "ravioli crema di noci": {"overall_score": 43.0, "sentiment_score": 48.0}, "ravioli alla zucca": {"overall_score": 28.5, "sentiment_score": 22.0}, "ravioli di porcini": {"overall_score": 7.0, "sentiment_score": 3.0}, "gnocchi sorrentina": {"overall_score": 50.0, "sentiment_score": 50.0}, "gnocchi ruggero": {"overall_score": 32.0, "sentiment_score": 31.0}, "lasagna vegetale": {"overall_score": 21.0, "sentiment_score": 33.0}, "gnocchi ai quattro formaggi": {"overall_score": 25.0, "sentiment_score": 41.0}, "risotto allo scoglio": {"overall_score": 33.0, "sentiment_score": 24.0}, "risotto san francisco": {"overall_score": 12.0, "sentiment_score": 16.0}, "risotto pescatore": {"overall_score": 18.5, "sentiment_score": 19.0}, "risotto porcini": {"overall_score": 45.0, "sentiment_score": 42.0}, "napoletana pizza": {"overall_score": 38.0, "sentiment_score": 35.0}, "don mario pizza": {"overall_score": 4.0, "sentiment_score": 6.0}, "mona lisa pizza": {"overall_score": 36.5, "sentiment_score": 27.0}, "de luxe pizza": {"overall_score": 2.0, "sentiment_score": 2.0}, "brigante pizza": {"overall_score": 15.0, "sentiment_score": 29.0}, "calzone al forno": {"overall_score": 44.0, "sentiment_score": 43.0}}