{"navin smoothie": {"overall_score": 13.0, "sentiment_score": 13.0}, "shrimp summer rolls": {"overall_score": 6.0, "sentiment_score": 7.0}, "tom kha goong soup": {"overall_score": 1.0, "sentiment_score": 1.0}, "silver salad": {"overall_score": 4.0, "sentiment_score": 5.0}, "bbq salmon salad": {"overall_score": 10.5, "sentiment_score": 10.0}, "golden noodles": {"overall_score": 7.0, "sentiment_score": 8.0}, "roast duck curry": {"overall_score": 8.0, "sentiment_score": 6.0}, "masmun curry ribs": {"overall_score": 3.0, "sentiment_score": 4.0}, "thai hot basil": {"overall_score": 10.5, "sentiment_score": 11.0}, "prik king": {"overall_score": 12.0, "sentiment_score": 12.0}, "grilled pork chops": {"overall_score": 5.0, "sentiment_score": 3.0}, "broccoli tofu": {"overall_score": 2.0, "sentiment_score": 2.0}, "golden fried rice": {"overall_score": 9.0, "sentiment_score": 9.0}}