{"eggs blackstone": {"overall_score": 15.0, "sentiment_score": 12.0}, "california benedict": {"overall_score": 1.0, "sentiment_score": 1.0}, "tortilla scramble": {"overall_score": 5.5, "sentiment_score": 7.0}, "chorizo scramble": {"overall_score": 2.0, "sentiment_score": 2.0}, "veggie scramble": {"overall_score": 14.0, "sentiment_score": 14.0}, "grilled artichoke": {"overall_score": 12.0, "sentiment_score": 10.0}, "potato skins": {"overall_score": 9.0, "sentiment_score": 8.0}, "chicken quesadilla": {"overall_score": 7.0, "sentiment_score": 6.0}, "buffalo tenders": {"overall_score": 10.0, "sentiment_score": 9.0}, "organic mixed greens salad": {"overall_score": 5.5, "sentiment_score": 5.0}, "penne pasta": {"overall_score": 8.0, "sentiment_score": 13.0}, "spaghetti and meatballs": {"overall_score": 11.0, "sentiment_score": 11.0}, "macaroni and cheese": {"overall_score": 4.0, "sentiment_score": 4.0}, "cornbread": {"overall_score": 13.0, "sentiment_score": 15.0}, "tomato juice": {"overall_score": 3.0, "sentiment_score": 3.0}}