{"sutter breakfast wrap": {"overall_score": 6.0, "sentiment_score": 7.0}, "smoked salmon bagel": {"overall_score": 8.0, "sentiment_score": 8.0}, "toast": {"overall_score": 7.0, "sentiment_score": 6.0}, "southwestern sandwich": {"overall_score": 5.0, "sentiment_score": 5.0}, "turkey cran sandwich": {"overall_score": 3.0, "sentiment_score": 3.0}, "vegan sandwich": {"overall_score": 2.0, "sentiment_score": 2.0}, "niman ranch pulled pork sandwich": {"overall_score": 1.0, "sentiment_score": 1.0}, "organic egg salad sandwich": {"overall_score": 4.0, "sentiment_score": 4.0}, "hash brown": {"overall_score": 9.0, "sentiment_score": 9.0}}