{"marina girl salad": {"overall_score": 10.5, "sentiment_score": 7.0}, "sopa de lima": {"overall_score": 1.0, "sentiment_score": 2.0}, "tacos dorados": {"overall_score": 4.0, "sentiment_score": 1.0}, "mucho gusto": {"overall_score": 9.0, "sentiment_score": 8.0}, "pasi\u00f3n": {"overall_score": 10.5, "sentiment_score": 10.0}, "margarita picante": {"overall_score": 2.0, "sentiment_score": 3.0}, "margarita fresca": {"overall_score": 14.0, "sentiment_score": 13.0}, "chicken chile verde": {"overall_score": 13.0, "sentiment_score": 12.0}, "housemade chorizo with potatoes": {"overall_score": 8.0, "sentiment_score": 14.0}, "traditional carnitas": {"overall_score": 6.0, "sentiment_score": 5.0}, "mushroom carnitas": {"overall_score": 12.0, "sentiment_score": 11.0}, "skirt steak carne asada": {"overall_score": 5.0, "sentiment_score": 6.0}, "refried beans": {"overall_score": 7.0, "sentiment_score": 9.0}, "grilled corn": {"overall_score": 3.0, "sentiment_score": 4.0}}