{"chana dal": {"overall_score": 7.0, "sentiment_score": 10.0}, "mutter paneer": {"overall_score": 5.0, "sentiment_score": 5.0}, "chicken coconut": {"overall_score": 10.0, "sentiment_score": 9.0}, "lamb jalfraizee": {"overall_score": 8.5, "sentiment_score": 7.0}, "chicken karahi": {"overall_score": 4.0, "sentiment_score": 4.0}, "fish karahi": {"overall_score": 8.5, "sentiment_score": 8.0}, "goat karahi": {"overall_score": 3.0, "sentiment_score": 3.0}, "lamb karahi": {"overall_score": 6.0, "sentiment_score": 6.0}, "prawn karahi": {"overall_score": 11.0, "sentiment_score": 11.0}, "chicken tikka kabab": {"overall_score": 13.0, "sentiment_score": 13.0}, "mixed fried rice": {"overall_score": 12.0, "sentiment_score": 14.0}, "chicken chili": {"overall_score": 14.0, "sentiment_score": 12.0}, "tamarind chutney": {"overall_score": 1.5, "sentiment_score": 1.5}, "mint chutney": {"overall_score": 1.5, "sentiment_score": 1.5}}