{"fresh maine lobster roll": [], "fresh dungeness crab roll": [], "mixed crab and lobster roll": [], " crab and  lobster roll": [], "half a roll with lobster": [], "half a roll with crab": [], "half a roll with both meats mixed": [], "seafood macncheese roll": [], "lobster garden salad": [], "crab garden salad": [], "mixed lobster and crab salad": [], " lobster and  crab garden salad": [], "garden salad with  crab": [], "garden salad with  lobster": [], "seafood garden salad": [], "taco salad": [], "oldfashioned allbeef hot dog": [], "surf and turf lobster dog": [], "surf and turf crab dog": [], "plain all beef hot dog": [], "cheese dog": [], "chili cheese dog": [], "bacon cheese dog": [], "chili dog": [], "lobster macncheese": [], "crab macncheese": [], "mixed crab and lobster macncheese": [], "macncheese with  crab": [], "macncheese with  lobster": [], " crab and  lobster macncheese": [], "chili macncheese": [], "chili macncheese dinner": [], "macncheese stroganoff": [], "macncheese stroganoff dinner": [], "new englandstyle puget sound clam chowder with bacon": [], "maine lobster bisque": [], "chili": [], "side of macncheese": [], "grilled split top roll": [], "dirty potato chips": [], "small side salad": [], "small side macncheese": [], "fresh popcorn": [], "small potato salad": [], "garlic bread roll": [], "small green salad": [], "fresh lobster cocktail": [], "crab cocktail": [], "crab and lobster cocktail": [], "lobster and veggies flat bread": [], "crab and veggies flat bread": [], "veggie flat bread": [], "margherita flat bread": [], "cheese flat bread": [], "lobster and crab veggie supreme flat bread": [], "plain nachos": [], "nachos supreme with  crab": [], "nachos supreme with  lobster": [], "nachos supreme with crab": [], "nachos supreme with lobster": [], "nachos supreme with  lobster and  crab": []}